{"hash":"cbda8e199e437bc457bb8ffce79198dda2037b07","data":{"post":{"title":"Interrail voorbereiding - West Europa","author":"","date":"2017-02-19","content":"<p>Tijd om alvast te bedenken wat we allemaal gaan meenemen gedurende onze treinreis en backpack tour.</p>\n<p>Waar beginnen we mee, eten natuurlijk!</p>\n<p><img src=\"https://www.danhnguyen.nl/wp-content/uploads//20170218_144700-700x394.jpg\" alt=\"20170218_144700\"></p>\n<p>Yeuy, Interrail passes zijn binnen.</p>\n<p><img src=\"https://www.danhnguyen.nl/wp-content/uploads//20170219_112228-700x394.jpg\" alt=\"20170219_112228\"></p>\n<p>Nu hotels boeken, natuurlijk via Booking.com aangezien ik genius member ben. We overnachten o.a. in plekken zoals Zwitserland (shiiiiit wat is dat duur daar), Italie en Duitsland.</p>\n","image":"https://www.danhnguyen.nl/wp-content/uploads/20170219_112228-700x394.jpg","category":{"title":"Interrail - Europa"}}},"context":{}}