{"hash":"cbda8e199e437bc457bb8ffce79198dda2037b07","data":{"post":{"title":"Day 13 - Oshiage, Skytree","author":"","date":"2014-09-27","content":"<p>Onze laatste dag in Tokyo. Morgen gaan we richting Kyoto! Vandaag dus even de laatste souvenir shopping gedaan en de super hoge Skytree Tower kunnen bekijken. Rondom de Skytree vind je een heleboel shops, waar leuke en ook rare dingen voorkomen.</p>\n<p><img src=\"https://www.danhnguyen.nl/wp-content/uploads//DSC03976-1024x575.jpg\" alt=\"DSC03976\"></p>\n<p>Kittycats!</p>\n<p><img src=\"https://www.danhnguyen.nl/wp-content/uploads//DSC03977-1024x575.jpg\" alt=\"DSC03977\"></p>\n<p>Miniature stuff.</p>\n<p><img src=\"https://www.danhnguyen.nl/wp-content/uploads//DSC03984-1024x575.jpg\" alt=\"DSC03984\"></p>\n<p>Kartonnen dingen.</p>\n<p><img src=\"https://www.danhnguyen.nl/wp-content/uploads//DSC03987-1024x575.jpg\" alt=\"DSC03987\"></p>\n<p>Hello kitties.</p>\n<p><img src=\"https://www.danhnguyen.nl/wp-content/uploads//DSC03990-1024x575.jpg\" alt=\"DSC03990\"></p>\n<p>Zoveel soorten soyasauce!</p>\n<p><img src=\"https://www.danhnguyen.nl/wp-content/uploads//DSC04001-1024x575.jpg\" alt=\"DSC04001\"></p>\n<p>Even rusten met Green Tea drink/ijs.</p>\n<p><img src=\"https://www.danhnguyen.nl/wp-content/uploads//IMG_4505-576x1024.jpg\" alt=\"IMG_4505\"></p>\n<p>Cheese!</p>\n<p><img src=\"https://www.danhnguyen.nl/wp-content/uploads//DSC04006-1024x575.jpg\" alt=\"DSC04006\"></p>\n<p>Nog een shot vanaf de 9e verdieping. Geen zin om 2000 Yen te betalen om in de Skytree te gaan. Goed, nu optijd slapen, hoop ik. Morgen ochtend laatste Ramen ontbijt en dan zoef met de High Speed Bullet Shinkansen trein naar Kyoto!</p>\n","image":"https://www.danhnguyen.nl/wp-content/uploads/DSC04006.jpg","category":{"title":"Tokyo, Kyoto, Osaka - Japan"}}},"context":{}}